duiker.py
duiker-0.1.0.dist-info/DESCRIPTION.rst
duiker-0.1.0.dist-info/METADATA
duiker-0.1.0.dist-info/RECORD
duiker-0.1.0.dist-info/WHEEL
duiker-0.1.0.dist-info/entry_points.txt
duiker-0.1.0.dist-info/metadata.json
duiker-0.1.0.dist-info/top_level.txt
