Metadata-Version: 2.0
Name: duiker
Version: 0.1.0
Summary: Automatically index your shell history in a full-text search database. Magic!
Home-page: https://github.com/benwebber/duiker/
Author: Ben Webber
Author-email: benjamin.webber@gmail.com
License: UNKNOWN
Platform: UNKNOWN
Classifier: Development Status :: 4 - Beta
Classifier: Programming Language :: Python :: 3
Classifier: Programming Language :: Python :: 3.5
Classifier: Programming Language :: Python :: 3.6
